kernax/AbstractKernel.py
kernax/__init__.py
kernax/config.py
kernax/distances.py
kernax/py.typed
kernax/transforms.py
kernax/utils.py
kernax/dotproduct/DotProductKernel.py
kernax/dotproduct/LinearKernel.py
kernax/dotproduct/PolynomialKernel.py
kernax/dotproduct/Sigmoid.py
kernax/dotproduct/__init__.py
kernax/operators/OperatorKernel.py
kernax/operators/ProductKernel.py
kernax/operators/SumKernel.py
kernax/operators/__init__.py
kernax/other/ConstantKernel.py
kernax/other/WhiteNoiseKernel.py
kernax/other/__init__.py
kernax/stationary/Matern12Kernel.py
kernax/stationary/Matern32Kernel.py
kernax/stationary/Matern52Kernel.py
kernax/stationary/PeriodicKernel.py
kernax/stationary/RationalQuadraticKernel.py
kernax/stationary/SEKernel.py
kernax/stationary/StationaryKernel.py
kernax/stationary/__init__.py
kernax/wrappers/ARDKernel.py
kernax/wrappers/ActiveDimsKernel.py
kernax/wrappers/BatchKernel.py
kernax/wrappers/BlockDiagKernel.py
kernax/wrappers/BlockKernel.py
kernax/wrappers/DiagKernel.py
kernax/wrappers/ExpKernel.py
kernax/wrappers/LogKernel.py
kernax/wrappers/NegKernel.py
kernax/wrappers/WrapperKernel.py
kernax/wrappers/__init__.py
kernax_ml-0.4.0a0.dist-info/licenses/LICENSE
kernax_ml-0.4.0a0.dist-info/METADATA
kernax_ml-0.4.0a0.dist-info/WHEEL
kernax_ml-0.4.0a0.dist-info/top_level.txt
kernax_ml-0.4.0a0.dist-info/RECORD
