Metadata-Version: 2.4
Name: kernax-ml
Version: 0.4.0a0
Summary: A JAX-based kernel library for Gaussian Processes with automatic differentiation and composable operations
Author-email: "S. Lejoly" <simon.lejoly@unamur.be>
Maintainer-email: "S. Lejoly" <simon.lejoly@unamur.be>
License: MIT
Project-URL: Homepage, https://github.com/SimLej18/kernax-ml
Project-URL: Repository, https://github.com/SimLej18/kernax-ml
Project-URL: Documentation, https://kernax-ml.readthedocs.io
Project-URL: Bug Tracker, https://github.com/SimLej18/kernax-ml/issues
Keywords: gaussian-processes,kernels,jax,machine-learning,covariance-functions,bayesian-optimization
Classifier: Development Status :: 3 - Alpha
Classifier: Intended Audience :: Science/Research
Classifier: Intended Audience :: Developers
Classifier: License :: OSI Approved :: MIT License
Classifier: Programming Language :: Python :: 3.12
Classifier: Topic :: Scientific/Engineering
Classifier: Topic :: Scientific/Engineering :: Artificial Intelligence
Classifier: Topic :: Scientific/Engineering :: Mathematics
Requires-Python: >=3.12
License-File: LICENSE
Requires-Dist: jax>=0.6.2
Requires-Dist: jaxlib>=0.6.2
Requires-Dist: equinox>=0.11.0
Provides-Extra: dev
Requires-Dist: pytest>=7.0; extra == "dev"
Requires-Dist: pytest-cov>=4.0; extra == "dev"
Requires-Dist: allure-pytest>=2.15; extra == "dev"
Requires-Dist: pytest-benchmark>=5.2; extra == "dev"
Requires-Dist: gpjax>=0.13; extra == "dev"
Requires-Dist: gpytorch>=1.15; extra == "dev"
Requires-Dist: scikit-learn>=1.8; extra == "dev"
Requires-Dist: ruff>=0.1.0; extra == "dev"
Requires-Dist: mypy>=0.990; extra == "dev"
Provides-Extra: docs
Requires-Dist: sphinx>=5.0; extra == "docs"
Requires-Dist: sphinx-rtd-theme>=1.0; extra == "docs"
Requires-Dist: nbsphinx>=0.8; extra == "docs"
Provides-Extra: benchmarks
Requires-Dist: pandas>=1.5.0; extra == "benchmarks"
Requires-Dist: matplotlib>=3.5.0; extra == "benchmarks"
Requires-Dist: jupyter>=1.0.0; extra == "benchmarks"
Dynamic: license-file
